pocketflow/__init__.py
pocketflow_framework/__init__.py
pocketflow_framework-0.0.1.dist-info/LICENSE
pocketflow_framework-0.0.1.dist-info/METADATA
pocketflow_framework-0.0.1.dist-info/WHEEL
pocketflow_framework-0.0.1.dist-info/top_level.txt
pocketflow_framework-0.0.1.dist-info/RECORD
