Metadata-Version: 2.2
Name: pocketflow_framework
Version: 0.0.1
Summary: Minimalist LLM Framework in 100 Lines. Enable LLMs to Program Themselves.
Home-page: https://github.com/The-Pocket-World/Pocketflow-Framework-Py
Author: Helena Zhang
Author-email: helenaz@stanford.edu
Classifier: Programming Language :: Python :: 3
Classifier: License :: OSI Approved :: MIT License
Classifier: Operating System :: OS Independent
Requires-Python: >=3.7
License-File: LICENSE
Dynamic: author
Dynamic: author-email
Dynamic: classifier
Dynamic: description
Dynamic: description-content-type
Dynamic: home-page
Dynamic: requires-python
Dynamic: summary
